gclang/__init__.py
gclang/__main__.py
gclang/guarded_exception.py
gclang/gen/GuardedLexer.py
gclang/gen/GuardedListener.py
gclang/gen/GuardedParser.py
gclang/gen/GuardedVisitor.py
gclang/gen/__init__.py
gclang/translate/__init__.py
gclang/translate/latex_visitor.py
gclang/translate/python_visitor.py
gclang-0.0.3.dist-info/LICENSE
gclang-0.0.3.dist-info/METADATA
gclang-0.0.3.dist-info/WHEEL
gclang-0.0.3.dist-info/entry_points.txt
gclang-0.0.3.dist-info/top_level.txt
gclang-0.0.3.dist-info/RECORD
