Metadata-Version: 2.1
Name: gclang
Version: 0.0.3
Summary: Guarded command language interpreter
Home-page: https://github.com/slmtnm/guarded
Author: Makar Solomatin
License: UNKNOWN
Platform: UNKNOWN
Requires-Dist: Click
Requires-Dist: antlr4-python3-runtime (==4.7.2)
Requires-Dist: click (==7.1.2)
Requires-Dist: sympy (==1.7.1)
